visualblocks/__init__.py
visualblocks/server.py
visualblocks-0.0.8.dist-info/METADATA
visualblocks-0.0.8.dist-info/WHEEL
visualblocks-0.0.8.dist-info/RECORD
