Metadata-Version: 2.1
Name: visualblocks
Version: 0.0.8
Summary: Visual Blocks for Google Colaboratory
Project-URL: Homepage, https://github.com/google/visualblocks
Project-URL: Bug Tracker, https://github.com/google/visualblocks/issues
Author-email: Google LLC <opensource@google.com>
Classifier: Environment :: Other Environment
Classifier: License :: OSI Approved :: Apache Software License
Classifier: Programming Language :: Python :: 3
Requires-Python: >=3.7
Requires-Dist: flask
Requires-Dist: google-colab
Requires-Dist: ipython
Requires-Dist: portpicker
